kisters/water/hydraulic_network/client/__init__.py
kisters/water/hydraulic_network/client/network.py
kisters.water.hydraulic_network.client-0.1.0.dist-info/LICENSE
kisters.water.hydraulic_network.client-0.1.0.dist-info/METADATA
kisters.water.hydraulic_network.client-0.1.0.dist-info/WHEEL
kisters.water.hydraulic_network.client-0.1.0.dist-info/top_level.txt
kisters.water.hydraulic_network.client-0.1.0.dist-info/RECORD
