Metadata-Version: 2.1
Name: kisters.water.hydraulic-network.client
Version: 0.1.0
Summary: Client library for the Kisters Hydraulic Network Storage service
Home-page: https://gitlab.com/kisters/water/hydraulic-network/client
Author: Jesse VanderWees
Author-email: jesse.vanderwees@kisters-bv.nl
License: UNKNOWN
Platform: UNKNOWN
Classifier: Programming Language :: Python :: 3.5
Classifier: Programming Language :: Python :: 3.6
Classifier: Programming Language :: Python :: 3.7
Classifier: License :: OSI Approved :: GNU Lesser General Public License v2 or later (LGPLv2+)
Classifier: Operating System :: OS Independent
Requires-Dist: kisters.water.hydraulic-network.models
Requires-Dist: kisters.water.rest-client
